crpto/__init__.py
crypt/__init__.py
crpto-0.0.3.dist-info/METADATA
crpto-0.0.3.dist-info/WHEEL
crpto-0.0.3.dist-info/top_level.txt
crpto-0.0.3.dist-info/RECORD
