Metadata-Version: 2.4
Name: crpto
Version: 0.0.3
Summary: Defensive registration - 'crypt' is a built-in module. Use pycryptodome or cryptography instead.
Author: Security Researcher
License-Expression: MIT
Project-URL: pycryptodome, https://pypi.org/project/pycryptodome/
Project-URL: cryptography, https://pypi.org/project/cryptography/
Keywords: typosquatting,security,crypt,crypto,protection
Requires-Python: >=3.6
Dynamic: requires-python
